{
    "activeTime":  [0.0, 120.0],
    "borders": [70, 70],
    "tickets": 3,
    "wave": [
        {
            "type": "SMALL",
            "buffedChance": 0.2,
            "delay": 0.4,
            "movement": "LINEAR",
            "offset": [0, 0]
        },
        {
            "type": "SMALL",
            "buffedChance": 0.0,
            "delay": 0.0,
            "movement": "LINEAR",
            "offset": [-30, 0]
        },
        {
            "type": "SMALL",
            "buffedChance": 0.0,
            "delay": 0.0,
            "movement": "LINEAR",
            "offset": [30, 0]
        }
    ]
}